pci_lmt/__init__.py
pci_lmt/args.py
pci_lmt/collector.py
pci_lmt/config.py
pci_lmt/constants.py
pci_lmt/device.py
pci_lmt/host.py
pci_lmt/pcie_lane_margining.py
pci_lmt/results.py
pci_lmt_bin/__init__.py
pci_lmt_bin/main.py
ocptv_pci_lmt-1.5.2.dist-info/LICENSE
ocptv_pci_lmt-1.5.2.dist-info/METADATA
ocptv_pci_lmt-1.5.2.dist-info/WHEEL
ocptv_pci_lmt-1.5.2.dist-info/entry_points.txt
ocptv_pci_lmt-1.5.2.dist-info/top_level.txt
ocptv_pci_lmt-1.5.2.dist-info/RECORD
