Metadata-Version: 2.2
Name: ocptv-pci_lmt
Version: 1.5.2
Summary: PCI Lane Margining Tool
Author-email: OCP Test & Validation <ocp-test-validation@OCP-All.groups.io>
License: MIT License
Project-URL: Homepage, https://github.com/opencomputeproject/ocp-diag-pci_lmt
Project-URL: Bug reports, https://github.com/opencomputeproject/ocp-diag-pci_lmt/issues
Project-URL: Source, https://github.com/opencomputeproject/ocp-diag-pci_lmt
Keywords: ocp,ocptv,pci,pcie,lmt
Classifier: License :: OSI Approved :: MIT License
Classifier: Programming Language :: Python
Classifier: Programming Language :: Python :: 3.8
Classifier: Topic :: System :: Hardware
Requires-Python: >=3.8
License-File: LICENSE
Provides-Extra: dev
Requires-Dist: black; extra == "dev"
Requires-Dist: bumpver; extra == "dev"
Requires-Dist: isort; extra == "dev"
Requires-Dist: pylint; extra == "dev"
Requires-Dist: mypy; extra == "dev"
Requires-Dist: build; extra == "dev"
Requires-Dist: twine; extra == "dev"
